{"id":"marmara","name":"Marmara","bbox":[25.8,39.7,30.4,41.8],"marks":[{"k":"hazard","n":"","c":[26.5108,40.5925],"lt":""},{"k":"hazard","n":"","c":[26.4213,40.2093],"lt":""},{"k":"hazard","n":"","c":[29.0017,41.0083],"lt":""},{"k":"hazard","n":"","c":[27.6988,40.4698],"lt":""},{"k":"hazard","n":"","c":[27.5017,40.4778],"lt":""},{"k":"hazard","n":"","c":[29.7996,40.7454],"lt":""},{"k":"hazard","n":"","c":[28.7383,41.043],"lt":""},{"k":"hazard","n":"Gelin Taşı","c":[27.721,40.5201],"lt":""},{"k":"hazard","n":"","c":[27.9731,40.3607],"lt":""},{"k":"hazard","n":"","c":[27.9731,40.3606],"lt":""},{"k":"hazard","n":"","c":[27.9732,40.3606],"lt":""},{"k":"hazard","n":"","c":[27.9731,40.3606],"lt":""},{"k":"hazard","n":"","c":[25.9571,41.7264],"lt":""},{"k":"hazard","n":"","c":[25.9572,41.7264],"lt":""},{"k":"hazard","n":"","c":[25.9569,41.7265],"lt":""},{"k":"hazard","n":"","c":[26.0511,41.712],"lt":""},{"k":"hazard","n":"","c":[26.0511,41.7121],"lt":""},{"k":"hazard","n":"","c":[25.9573,40.1235],"lt":""},{"k":"hazard","n":"","c":[25.9573,40.1236],"lt":""},{"k":"hazard","n":"","c":[25.9579,40.1234],"lt":""},{"k":"hazard","n":"","c":[25.9581,40.1234],"lt":""},{"k":"hazard","n":"","c":[25.9582,40.1233],"lt":""},{"k":"hazard","n":"","c":[25.9587,40.1235],"lt":""},{"k":"hazard","n":"","c":[25.9589,40.1235],"lt":""},{"k":"hazard","n":"","c":[25.9636,40.1239],"lt":""},{"k":"hazard","n":"","c":[25.9639,40.1241],"lt":""},{"k":"hazard","n":"","c":[25.9647,40.1244],"lt":""},{"k":"hazard","n":"","c":[25.9679,40.1258],"lt":""},{"k":"hazard","n":"","c":[25.9718,40.1252],"lt":""},{"k":"hazard","n":"","c":[25.9725,40.1251],"lt":""},{"k":"hazard","n":"","c":[25.9706,40.1259],"lt":""},{"k":"hazard","n":"","c":[25.9039,40.2361],"lt":""},{"k":"hazard","n":"","c":[25.9041,40.2364],"lt":""},{"k":"hazard","n":"","c":[25.9044,40.2367],"lt":""},{"k":"hazard","n":"","c":[25.9051,40.237],"lt":""},{"k":"hazard","n":"","c":[25.9103,40.2362],"lt":""},{"k":"hazard","n":"","c":[25.9111,40.2368],"lt":""},{"k":"hazard","n":"","c":[25.9117,40.2367],"lt":""},{"k":"hazard","n":"Kırklareli Barajı Seyir Tepesi","c":[27.2928,41.7821],"lt":""},{"k":"hazard","n":"","c":[26.4975,40.587],"lt":""},{"k":"hazard","n":"","c":[29.0833,41.2667],"lt":""},{"k":"hazard","n":"","c":[27.4875,40.859],"lt":""},{"k":"hazard","n":"","c":[29.151,41.219],"lt":""},{"k":"hazard","n":"","c":[27.111,40.4567],"lt":""},{"k":"hazard","n":"","c":[29.1267,41.215],"lt":""},{"k":"hazard","n":"","c":[28.6517,40.9605],"lt":""},{"k":"hazard","n":"","c":[29.2868,41.2297],"lt":""},{"k":"hazard","n":"","c":[29.0895,41.1967],"lt":""},{"k":"hazard","n":"","c":[29.943,41.1672],"lt":""},{"k":"hazard","n":"","c":[29.9678,41.17],"lt":""},{"k":"hazard","n":"","c":[29.0478,41.077],"lt":""},{"k":"hazard","n":"","c":[26.2522,40.3036],"lt":""},{"k":"hazard","n":"","c":[26.2411,40.3128],"lt":""},{"k":"hazard","n":"","c":[26.5108,40.5917],"lt":""},{"k":"hazard","n":"","c":[27.0586,40.4183],"lt":""},{"k":"hazard","n":"ATENE (POSSIBLY)","c":[28.8045,41.3004],"lt":""},{"k":"hazard","n":"","c":[28.8531,41.2837],"lt":""},{"k":"hazard","n":"","c":[29.0764,41.1525],"lt":""},{"k":"hazard","n":"","c":[29.0603,41.2576],"lt":""},{"k":"hazard","n":"ATHOS 11","c":[29.2227,41.2301],"lt":""},{"k":"hazard","n":"ARDA","c":[29.293,41.224],"lt":""},{"k":"hazard","n":"","c":[29.1125,41.1898],"lt":""},{"k":"hazard","n":"","c":[26.036,40.6323],"lt":""},{"k":"hazard","n":"","c":[27.1177,40.6067],"lt":""},{"k":"hazard","n":"MARLENE","c":[29.223,41.2337],"lt":""},{"k":"hazard","n":"WORLD HARMONY","c":[29.0694,41.1367],"lt":""},{"k":"hazard","n":"","c":[29.0775,41.179],"lt":""},{"k":"hazard","n":"DENIZATI","c":[29.0677,41.1311],"lt":""},{"k":"hazard","n":"","c":[29.1133,41.2367],"lt":""},{"k":"hazard","n":"MUREFTE (POSSIBLY)","c":[29.1203,41.2082],"lt":""},{"k":"hazard","n":"","c":[29.1096,41.1953],"lt":""},{"k":"hazard","n":"","c":[27.9637,40.9696],"lt":""},{"k":"hazard","n":"RABUNION VXIII","c":[29.0573,41.0899],"lt":""},{"k":"hazard","n":"LOK PRABHA (STERN SECTION)","c":[29.0581,41.0851],"lt":""},{"k":"hazard","n":"","c":[29.0682,41.1118],"lt":""},{"k":"hazard","n":"","c":[28.8428,41.289],"lt":""},{"k":"hazard","n":"","c":[27.3078,40.6307],"lt":""},{"k":"hazard","n":"","c":[29.113,41.1874],"lt":""},{"k":"hazard","n":"LINA","c":[29.1645,41.224],"lt":""},{"k":"hazard","n":"","c":[29.1017,41.2041],"lt":""},{"k":"hazard","n":"DRAGON","c":[29.0562,41.1557],"lt":""},{"k":"hazard","n":"SOYDAN OKAN","c":[29.0559,41.144],"lt":""},{"k":"hazard","n":"LOK PRABHA (BOW SECTION(","c":[29.0594,41.0869],"lt":""},{"k":"hazard","n":"","c":[29.0958,41.1192],"lt":""},{"k":"hazard","n":"KAPTAN CELAL.","c":[29.1667,41.25],"lt":""},{"k":"hazard","n":"VADI","c":[27.4995,40.5823],"lt":""},{"k":"hazard","n":"ARMENI","c":[29.1228,41.214],"lt":""},{"k":"hazard","n":"HAMDI ISMET","c":[29.2245,41.2407],"lt":""},{"k":"hazard","n":"","c":[28.9217,40.9839],"lt":""},{"k":"hazard","n":"KAPRIJE","c":[27.4667,40.6833],"lt":""},{"k":"hazard","n":"YASAR SAHIN","c":[29.6,41.1833],"lt":""},{"k":"hazard","n":"TARA","c":[27.3278,40.7323],"lt":""},{"k":"hazard","n":"","c":[27.9633,40.9695],"lt":""},{"k":"hazard","n":"ZEA","c":[30.2833,41.2083],"lt":""},{"k":"hazard","n":"","c":[29.272,41.2304],"lt":""},{"k":"hazard","n":"ABDELKADER","c":[27.975,40.9167],"lt":""},{"k":"hazard","n":"ADANA","c":[29.3667,41.4],"lt":""},{"k":"hazard","n":"BRAINPOWER","c":[29.0412,41.0657],"lt":""},{"k":"hazard","n":"LORNA I","c":[29.3333,41.5],"lt":""},{"k":"hazard","n":"TATVAN","c":[28.6828,41.349],"lt":""},{"k":"hazard","n":"BLACK SEA","c":[29.1662,41.3323],"lt":""},{"k":"hazard","n":"TAHSIN INANDI","c":[28.8,41.3167],"lt":""},{"k":"hazard","n":"BOLERO","c":[28.6883,41.35],"lt":""},{"k":"hazard","n":"","c":[29.0687,41.1129],"lt":""},{"k":"hazard","n":"","c":[29.1,41.1208],"lt":""},{"k":"hazard","n":"","c":[29.0772,41.1486],"lt":""},{"k":"hazard","n":"DEMIRCI I","c":[30.25,41.25],"lt":""},{"k":"hazard","n":"HACI IBRAHIM","c":[28.8328,40.7323],"lt":""},{"k":"hazard","n":"","c":[26.5151,40.5893],"lt":""},{"k":"hazard","n":"FULGERUL OR NALUCA","c":[28.9828,41.249],"lt":""},{"k":"hazard","n":"","c":[28.6545,40.9572],"lt":""},{"k":"hazard","n":"","c":[25.9995,40.7132],"lt":""},{"k":"hazard","n":"","c":[25.9982,40.7163],"lt":""},{"k":"hazard","n":"DOHAN ASLAN LTV","c":[26.8664,40.5005],"lt":""},{"k":"hazard","n":"","c":[27.3165,40.7047],"lt":""},{"k":"hazard","n":"","c":[29.26,40.855],"lt":""},{"k":"hazard","n":"","c":[28.969,41.0213],"lt":""},{"k":"hazard","n":"VOLGONEFT 248","c":[28.9412,40.6073],"lt":""},{"k":"hazard","n":"","c":[25.805,39.9492],"lt":""},{"k":"hazard","n":"","c":[28.7237,40.929],"lt":""},{"k":"hazard","n":"","c":[28.6767,40.9042],"lt":""},{"k":"hazard","n":"","c":[28.8482,40.7085],"lt":""},{"k":"hazard","n":"","c":[29.0658,40.7453],"lt":""},{"k":"hazard","n":"","c":[25.805,39.9992],"lt":""},{"k":"hazard","n":"","c":[25.8715,39.9963],"lt":""},{"k":"hazard","n":"","c":[26.0688,40.5938],"lt":""},{"k":"hazard","n":"","c":[29.2763,40.8538],"lt":""},{"k":"hazard","n":"","c":[29.266,40.8354],"lt":""},{"k":"hazard","n":"","c":[29.2443,40.8726],"lt":""},{"k":"hazard","n":"","c":[29.2472,40.8708],"lt":""},{"k":"hazard","n":"","c":[26.8232,40.4477],"lt":""},{"k":"hazard","n":"RABUNION XIV","c":[26.3962,40.149],"lt":""},{"k":"hazard","n":"","c":[26.4059,40.1532],"lt":""},{"k":"hazard","n":"","c":[29.9359,40.7196],"lt":""},{"k":"hazard","n":"","c":[29.9112,40.7156],"lt":""},{"k":"hazard","n":"","c":[29.9205,40.7592],"lt":""},{"k":"hazard","n":"","c":[29.9002,40.7167],"lt":""},{"k":"hazard","n":"","c":[29.8962,40.7185],"lt":""},{"k":"hazard","n":"","c":[29.8972,40.7184],"lt":""},{"k":"hazard","n":"","c":[29.7973,40.7437],"lt":""},{"k":"hazard","n":"","c":[29.912,40.7601],"lt":""},{"k":"hazard","n":"","c":[29.9212,40.7601],"lt":""},{"k":"hazard","n":"","c":[29.7553,40.7497],"lt":""},{"k":"hazard","n":"","c":[29.8303,40.747],"lt":""},{"k":"hazard","n":"","c":[29.8309,40.7219],"lt":""},{"k":"hazard","n":"","c":[29.8753,40.7226],"lt":""},{"k":"hazard","n":"","c":[29.834,40.7493],"lt":""},{"k":"hazard","n":"","c":[29.9153,40.7593],"lt":""},{"k":"hazard","n":"","c":[29.9117,40.7152],"lt":""},{"k":"hazard","n":"","c":[29.6067,40.6933],"lt":""},{"k":"hazard","n":"","c":[29.3995,40.7559],"lt":""},{"k":"hazard","n":"","c":[29.606,40.7158],"lt":""},{"k":"hazard","n":"","c":[29.4328,40.6917],"lt":""},{"k":"hazard","n":"","c":[29.5262,40.7493],"lt":""},{"k":"hazard","n":"","c":[29.4006,40.7293],"lt":""},{"k":"hazard","n":"HMS HYTHE","c":[26.087,40.0207],"lt":""},{"k":"hazard","n":"","c":[26.1812,40.0407],"lt":""},{"k":"hazard","n":"","c":[26.0695,40.0809],"lt":""},{"k":"hazard","n":"","c":[26.0809,40.0359],"lt":""},{"k":"hazard","n":"MASSEUA","c":[26.1731,40.0415],"lt":""},{"k":"hazard","n":"","c":[28.6775,40.9656],"lt":""},{"k":"hazard","n":"","c":[26.075,40.0362],"lt":""},{"k":"hazard","n":"HMS TRIUMPH (POSSIBLY)","c":[26.2328,40.2015],"lt":""},{"k":"hazard","n":"","c":[25.9617,39.8353],"lt":""},{"k":"hazard","n":"HMS MAJESTIC","c":[26.1649,40.0438],"lt":""},{"k":"hazard","n":"","c":[25.8532,39.9492],"lt":""},{"k":"hazard","n":"","c":[26.2247,40.2432],"lt":""},{"k":"hazard","n":"","c":[25.8767,39.8083],"lt":""},{"k":"hazard","n":"","c":[26.0767,39.7914],"lt":""},{"k":"hazard","n":"","c":[26.2245,40.1737],"lt":""},{"k":"hazard","n":"","c":[26.0028,39.8487],"lt":""},{"k":"hazard","n":"","c":[26.0584,39.789],"lt":""},{"k":"hazard","n":"","c":[25.8525,40.0243],"lt":""},{"k":"hazard","n":"","c":[26.1812,40.0741],"lt":""},{"k":"hazard","n":"","c":[26.1654,40.0494],"lt":""},{"k":"hazard","n":"","c":[25.968,40.1512],"lt":""},{"k":"hazard","n":"","c":[25.947,40.2305],"lt":""},{"k":"hazard","n":"","c":[25.9815,39.9975],"lt":""},{"k":"hazard","n":"","c":[27.8698,40.8075],"lt":""},{"k":"hazard","n":"IVAN SECHENOV","c":[27.6333,40.8],"lt":""},{"k":"hazard","n":"PL-1-0531","c":[27.9678,40.359],"lt":""},{"k":"hazard","n":"","c":[27.954,40.3617],"lt":""},{"k":"hazard","n":"","c":[27.9983,40.4387],"lt":""},{"k":"hazard","n":"SELIM CAVUSOGLU","c":[27.632,40.799],"lt":""},{"k":"hazard","n":"KASIM KAPTAN","c":[28.0662,40.4657],"lt":""},{"k":"hazard","n":"TAYYAR SENKAYA","c":[28.5495,40.5157],"lt":""},{"k":"hazard","n":"AL FARES","c":[27.5672,40.6856],"lt":""},{"k":"hazard","n":"","c":[27.5151,40.5462],"lt":""},{"k":"hazard","n":"RABUNION II","c":[27.6333,40.6667],"lt":""},{"k":"hazard","n":"","c":[27.6907,40.4723],"lt":""},{"k":"hazard","n":"","c":[28.1043,40.4403],"lt":""},{"k":"hazard","n":"LUCANO, DELORO MICHIGAN & ORUBA","c":[25.9706,40.15],"lt":""},{"k":"hazard","n":"","c":[25.9839,40.1506],"lt":""},{"k":"hazard","n":"","c":[25.9489,40.2272],"lt":""},{"k":"hazard","n":"HMS KINROSS","c":[25.8617,40.0022],"lt":""},{"k":"hazard","n":"HMS M.28","c":[25.9611,40.2278],"lt":""},{"k":"hazard","n":"","c":[26.0083,40.1625],"lt":""},{"k":"hazard","n":"HMS DUCHESS OF RICHMOND","c":[25.8444,40.0478],"lt":""},{"k":"hazard","n":"BRESLAU","c":[25.9798,40.0618],"lt":""},{"k":"hazard","n":"","c":[26.0533,40.1539],"lt":""},{"k":"hazard","n":"","c":[26.1314,39.8011],"lt":""},{"k":"hazard","n":"NEWCASTLE CITY","c":[25.9662,39.8657],"lt":""},{"k":"hazard","n":"PELMARINER","c":[25.8595,39.804],"lt":""},{"k":"hazard","n":"","c":[26.0028,39.8123],"lt":""},{"k":"hazard","n":"","c":[25.9662,39.824],"lt":""},{"k":"hazard","n":"","c":[25.9922,39.9168],"lt":""},{"k":"hazard","n":"","c":[26.0741,39.8338],"lt":""},{"k":"hazard","n":"","c":[26.0828,39.8348],"lt":""},{"k":"hazard","n":"","c":[26.0764,39.8376],"lt":""},{"k":"hazard","n":"","c":[25.8828,39.799],"lt":""},{"k":"hazard","n":"","c":[29.1129,40.9175],"lt":""},{"k":"hazard","n":"","c":[26.6653,40.4033],"lt":""},{"k":"hazard","n":"","c":[26.4012,40.1871],"lt":""},{"k":"hazard","n":"","c":[26.4054,40.1882],"lt":""},{"k":"hazard","n":"","c":[26.4041,40.1872],"lt":""},{"k":"hazard","n":"","c":[26.4037,40.1876],"lt":""},{"k":"hazard","n":"CAPOPINO","c":[26.3812,40.2068],"lt":""},{"k":"hazard","n":"","c":[26.3999,40.1793],"lt":""},{"k":"hazard","n":"","c":[26.4056,40.1818],"lt":""},{"k":"hazard","n":"","c":[26.4144,40.18],"lt":""},{"k":"hazard","n":"","c":[26.4047,40.1833],"lt":""},{"k":"hazard","n":"","c":[26.5639,40.2583],"lt":""},{"k":"hazard","n":"","c":[26.6507,40.4004],"lt":""},{"k":"hazard","n":"","c":[26.7045,40.3722],"lt":""},{"k":"hazard","n":"HALEB, KHIOS, TENEDOS, TOUZLA, UNKNOWN","c":[26.4333,40.2333],"lt":""},{"k":"hazard","n":"YOUSSEF","c":[26.7821,40.4124],"lt":""},{"k":"hazard","n":"NOOR AL AMAL","c":[26.7329,40.4323],"lt":""},{"k":"hazard","n":"","c":[25.8625,40.2241],"lt":""},{"k":"hazard","n":"","c":[26.3993,40.1738],"lt":""},{"k":"hazard","n":"","c":[26.392,40.2035],"lt":""},{"k":"hazard","n":"","c":[26.4305,40.2288],"lt":""},{"k":"hazard","n":"","c":[26.2203,40.0367],"lt":""},{"k":"hazard","n":"TURNU SEVERIN","c":[26.3529,40.1172],"lt":""},{"k":"hazard","n":"","c":[29.8664,40.7325],"lt":""},{"k":"hazard","n":"","c":[25.8785,40.8436],"lt":""},{"k":"hazard","n":"PANAYIA KASTRO","c":[25.8803,40.8402],"lt":""},{"k":"hazard","n":"","c":[25.8892,40.8425],"lt":""},{"k":"hazard","n":"","c":[25.8924,40.7986],"lt":""},{"k":"hazard","n":"","c":[28.9859,41.0239],"lt":""},{"k":"hazard","n":"","c":[29.4817,40.7437],"lt":""},{"k":"hazard","n":"","c":[29.2178,40.8768],"lt":""},{"k":"hazard","n":"","c":[29.2944,40.8128],"lt":""},{"k":"hazard","n":"","c":[28.9431,40.9913],"lt":""},{"k":"hazard","n":"","c":[27.641,40.363],"lt":""},{"k":"hazard","n":"","c":[28.9661,40.9158],"lt":""},{"k":"hazard","n":"KEMAL KEFELI","c":[29.0114,41.0339],"lt":""},{"k":"hazard","n":"","c":[29.0493,40.9553],"lt":""},{"k":"hazard","n":"","c":[29.0,41.0315],"lt":""},{"k":"hazard","n":"","c":[29.0971,40.9194],"lt":""},{"k":"hazard","n":"","c":[28.9818,41.021],"lt":""},{"k":"hazard","n":"","c":[29.1117,40.8688],"lt":""},{"k":"hazard","n":"","c":[28.9834,40.8999],"lt":""},{"k":"hazard","n":"","c":[29.0004,41.0285],"lt":""},{"k":"hazard","n":"","c":[28.9914,41.025],"lt":""},{"k":"hazard","n":"","c":[28.989,41.0232],"lt":""},{"k":"hazard","n":"","c":[28.977,41.0207],"lt":""},{"k":"hazard","n":"","c":[28.8793,40.9662],"lt":""},{"k":"hazard","n":"MEHMET METE","c":[29.0053,41.0319],"lt":""},{"k":"hazard","n":"","c":[29.1662,40.8161],"lt":""},{"k":"hazard","n":"","c":[29.0054,41.033],"lt":""},{"k":"hazard","n":"","c":[28.8828,40.9691],"lt":""},{"k":"hazard","n":"","c":[29.2048,40.8818],"lt":""},{"k":"hazard","n":"","c":[29.1027,40.9411],"lt":""},{"k":"hazard","n":"HIKMET DEVAL","c":[29.0,40.9167],"lt":""},{"k":"hazard","n":"","c":[28.9145,40.9807],"lt":""},{"k":"hazard","n":"","c":[28.9345,40.9912],"lt":""},{"k":"hazard","n":"","c":[28.8343,40.9012],"lt":""},{"k":"hazard","n":"","c":[28.9509,41.0359],"lt":""},{"k":"hazard","n":"D3","c":[29.0208,41.0389],"lt":""},{"k":"hazard","n":"","c":[29.0028,41.0256],"lt":""},{"k":"hazard","n":"PIENKI-DERVA","c":[28.8958,40.9694],"lt":""},{"k":"hazard","n":"LUKULL","c":[28.9958,41.025],"lt":""},{"k":"hazard","n":"GREGORY GAPONOFF","c":[28.9833,41.0],"lt":""},{"k":"hazard","n":"ORHAN ZINDANCIOGLU II","c":[28.9995,40.999],"lt":""},{"k":"hazard","n":"","c":[28.8162,40.8657],"lt":""},{"k":"hazard","n":"","c":[28.8862,40.9707],"lt":""},{"k":"hazard","n":"USKADARLI I","c":[28.8884,40.9759],"lt":""},{"k":"hazard","n":"MARIETTA POLANSA","c":[29.0111,40.9944],"lt":""},{"k":"hazard","n":"","c":[29.0042,41.0278],"lt":""},{"k":"hazard","n":"IRINI K","c":[28.9567,41.0047],"lt":""},{"k":"hazard","n":"","c":[28.9768,41.0002],"lt":""},{"k":"hazard","n":"SEMELE","c":[28.9745,40.999],"lt":""},{"k":"hazard","n":"INDEPENDENTA","c":[29.0073,40.9932],"lt":""},{"k":"hazard","n":"","c":[29.02,40.9972],"lt":""},{"k":"hazard","n":"","c":[29.0042,41.0042],"lt":""},{"k":"hazard","n":"","c":[28.9958,41.0222],"lt":""},{"k":"hazard","n":"MARIE VAGLIANO","c":[28.9833,40.9917],"lt":""},{"k":"hazard","n":"","c":[29.0083,41.0333],"lt":""},{"k":"hazard","n":"","c":[27.4,40.355],"lt":""},{"k":"hazard","n":"","c":[29.2825,40.7867],"lt":""},{"k":"hazard","n":"","c":[29.0653,40.8864],"lt":""},{"k":"hazard","n":"Çamalti Burnu 1","c":[27.5235,40.643],"lt":""},{"k":"hazard","n":"Anata?  Adacik (Palapetra)","c":[27.5482,40.6565],"lt":""},{"k":"hazard","n":"Yenikapı Batıkları","c":[28.9521,41.0061],"lt":""},{"k":"hazard","n":"Agatocle Batığı","c":[29.5267,40.7503],"lt":""},{"k":"hazard","n":"Najade (gemi)","c":[27.5667,40.5667],"lt":""},{"k":"hazard","n":"HMAS AE2","c":[28.0752,40.6724],"lt":""},{"k":"hazard","n":"HMS Bouvet Batığı","c":[26.2966,40.0405],"lt":""},{"k":"hazard","n":"HMS Arno (1915)","c":[26.5083,40.2417],"lt":""},{"k":"hazard","n":"Halep Vapuru","c":[26.4492,40.2195],"lt":""},{"k":"hazard","n":"HMS E15","c":[26.3711,40.1032],"lt":""},{"k":"hazard","n":"HMS Irresistible (1898)","c":[26.3166,40.0333],"lt":""},{"k":"hazard","n":"SS Milo Batığı","c":[26.2792,40.2413],"lt":""},{"k":"hazard","n":"HMS Majestic (1895)","c":[26.1839,40.0417],"lt":""},{"k":"hazard","n":"HMS Triumph","c":[26.25,40.0333],"lt":""},{"k":"hazard","n":"HMS Goliath","c":[26.2,40.0333],"lt":""},{"k":"hazard","n":"HMS Ocean","c":[26.2998,40.0165],"lt":""},{"k":"hazard","n":"HMS M28","c":[25.9628,40.2286],"lt":""},{"k":"hazard","n":"HMS Raglan","c":[25.9667,40.2333],"lt":""},{"k":"hazard","n":"","c":[26.323,40.1872],"lt":""},{"k":"hazard","n":"Тракийско светилище - Глухите камъни","c":[25.9555,41.7274],"lt":""},{"k":"hazard","n":"","c":[25.9548,41.7278],"lt":""},{"k":"hazard","n":"","c":[25.9559,41.7275],"lt":""},{"k":"hazard","n":"","c":[25.9559,41.7273],"lt":""},{"k":"hazard","n":"","c":[25.9562,41.7272],"lt":""},{"k":"hazard","n":"","c":[29.1155,41.234],"lt":""},{"k":"hazard","n":"Manastır Adası","c":[27.8032,40.5177],"lt":""},{"k":"hazard","n":"Kuşkaya","c":[28.3564,41.3414],"lt":""},{"k":"hazard","n":"Кралимарков камък","c":[26.052,41.7093],"lt":""},{"k":"hazard","n":"","c":[28.3582,41.341],"lt":""},{"k":"hazard","n":"","c":[28.3575,41.3415],"lt":""},{"k":"hazard","n":"","c":[28.2401,41.496],"lt":""},{"k":"hazard","n":"","c":[28.2054,41.5177],"lt":""},{"k":"hazard","n":"","c":[28.2176,41.5181],"lt":""},{"k":"hazard","n":"","c":[28.1727,41.5766],"lt":""},{"k":"hazard","n":"","c":[28.1752,41.5728],"lt":""},{"k":"hazard","n":"","c":[25.9569,41.7261],"lt":""},{"k":"hazard","n":"","c":[25.9567,41.7262],"lt":""},{"k":"hazard","n":"","c":[25.9562,41.7263],"lt":""},{"k":"hazard","n":"","c":[27.5008,41.7504],"lt":""},{"k":"hazard","n":"Ambarkaya Trak Sunağı","c":[27.5224,41.6347],"lt":""},{"k":"hazard","n":"","c":[27.5638,41.6474],"lt":""},{"k":"hazard","n":"","c":[27.4915,41.7699],"lt":""},{"k":"hazard","n":"","c":[27.9069,41.6723],"lt":""},{"k":"hazard","n":"","c":[27.9098,41.6696],"lt":""},{"k":"hazard","n":"","c":[27.9815,41.7076],"lt":""},{"k":"hazard","n":"","c":[27.9762,41.7466],"lt":""},{"k":"hazard","n":"","c":[27.976,41.7468],"lt":""},{"k":"fishfarm","n":"abandonend fishfarm","c":[29.23,40.5705],"lt":""},{"k":"fishfarm","n":"abandonend fishfarm","c":[29.2301,40.5704],"lt":""},{"k":"fishfarm","n":"abandonend fishfarm","c":[29.2301,40.5702],"lt":""},{"k":"fishfarm","n":"Abandonend fishfarm","c":[29.2301,40.5701],"lt":""},{"k":"fishfarm","n":"Testili Kızlar","c":[28.6853,41.0642],"lt":""},{"k":"fishfarm","n":"Alabalık","c":[27.9802,41.6121],"lt":""},{"k":"fishfarm","n":"Alabalık","c":[27.9794,41.612],"lt":""},{"k":"fishfarm","n":"Alabalık","c":[27.9831,41.616],"lt":""},{"k":"fishfarm","n":"","c":[27.9884,41.621],"lt":""},{"k":"fishfarm","n":"","c":[27.9881,41.6211],"lt":""},{"k":"fishfarm","n":"","c":[27.988,41.6213],"lt":""},{"k":"fishfarm","n":"","c":[27.7951,40.3291],"lt":""},{"k":"fishfarm","n":"Narlı Midye Çiftliği","c":[27.7077,40.4635],"lt":""},{"k":"fishfarm","n":"Çakıl Midye Çiftliği","c":[28.0711,40.4534],"lt":""}]}